py_fumen_util/__init__.py
py_fumen_util/__main__.py
py_fumen_util/assemble.py
py_fumen_util/disassemble.py
py_fumen_util/grayout.py
py_fumen_util/grayout_all.py
py_fumen_util/join.py
py_fumen_util/lock.py
py_fumen_util/mirror.py
py_fumen_util/prune.py
py_fumen_util/prune_all.py
py_fumen_util/split.py
py_fumen_util/uncomment.py
py_fumen_util-0.3.1.dist-info/METADATA
py_fumen_util-0.3.1.dist-info/WHEEL
py_fumen_util-0.3.1.dist-info/licenses/LICENSE
py_fumen_util-0.3.1.dist-info/RECORD
