Metadata-Version: 2.1
Name: py_fumen_util
Version: 0.3.1
Summary: Python implementation of the JavaScript package 'FumenUtil'
Project-URL: Source, https://github.com/OctupusTea/py-fumen-util
Author: Octupus Tea
License-File: LICENSE
Classifier: License :: OSI Approved :: MIT License
Classifier: Operating System :: OS Independent
Classifier: Programming Language :: Python :: 3
Requires-Python: >=3.8
